ncm/__init__.py
ncm/network.py
neural_circuit_machine-0.1.0.dist-info/METADATA
neural_circuit_machine-0.1.0.dist-info/WHEEL
neural_circuit_machine-0.1.0.dist-info/RECORD
