Metadata-Version: 2.4
Name: neural-circuit-machine
Version: 0.1.0
Summary: Add your description here
Project-URL: Homepage, https://github.com/yashbonde/neural-circuit-machine
Project-URL: Repository, https://github.com/yashbonde/neural-circuit-machine.git
Project-URL: Documentation, https://github.com/yashbonde/neural-circuit-machine#readme
Requires-Python: >=3.13
Requires-Dist: fire>=0.7.0
Requires-Dist: ipykernel==6.29.5
Requires-Dist: matplotlib>=3.10.7
Requires-Dist: numpy>=2.3.4
Requires-Dist: torch>=2.9.0
Requires-Dist: tuneapi>=8.0.33
Requires-Dist: twine>=6.1.0
